{"timestamp": "2023-01-10T13:07:00.022Z", "countryPairs": [{"options": ["\u010ce\u0161ka", "Poljska"], "key": "\u010ce\u0161ka::Poljska", "selected": "\u010ce\u0161ka"}, {"options": ["Slovenija", "Belgija"], "key": "Slovenija::Belgija", "selected": "Slovenija"}, {"options": ["Norve\u0161ka", "Islandija"], "key": "Norve\u0161ka::Islandija", "selected": "Norve\u0161ka"}, {"options": ["Finska", "Srbija"], "key": "Finska::Srbija", "selected": "Finska"}, {"options": ["Norve\u0161ka", "Avstrija"], "key": "Norve\u0161ka::Avstrija", "selected": "Avstrija"}, {"options": ["Francija", "Romunija"], "key": "Francija::Romunija", "selected": "Francija"}, {"options": ["\u0160panija", "Islandija"], "key": "\u0160panija::Islandija", "selected": "\u0160panija"}, {"options": ["Litva", "Avstrija"], "key": "Litva::Avstrija", "selected": "Avstrija"}, {"options": ["Avstrija", "Estonija"], "key": "Avstrija::Estonija", "selected": "Avstrija"}, {"options": ["Latvija", "Nem\u010dija"], "key": "Latvija::Nem\u010dija", "selected": "Nem\u010dija"}, {"options": ["Belgija", "Latvija"], "key": "Belgija::Latvija", "selected": "Belgija"}, {"options": ["Danska", "Finska"], "key": "Danska::Finska", "selected": "Danska"}, {"options": ["Litva", "\u0160vica"], "key": "Litva::\u0160vica", "selected": "\u0160vica"}, {"options": ["Litva", "Irska"], "key": "Litva::Irska", "selected": "Irska"}, {"options": ["Belgija", "Portugalska"], "key": "Belgija::Portugalska", "selected": "Belgija"}, {"options": ["Litva", "Portugalska"], "key": "Litva::Portugalska", "selected": "Portugalska"}, {"options": ["Portugalska", "\u010crna gora"], "key": "Portugalska::\u010crna gora", "selected": "Portugalska"}, {"options": ["Srbija", "Tur\u010dija"], "key": "Srbija::Tur\u010dija", "selected": "Srbija"}, {"options": ["\u010ce\u0161ka", "Slova\u0161ka"], "key": "\u010ce\u0161ka::Slova\u0161ka", "selected": "\u010ce\u0161ka"}, {"options": ["Nizozemska", "Litva"], "key": "Nizozemska::Litva", "selected": "Nizozemska"}, {"options": ["Nizozemska", "Severna Makedonija"], "key": "Nizozemska::Severna Makedonija", "selected": "Nizozemska"}, {"options": ["Srbija", "Francija"], "key": "Srbija::Francija", "selected": "Francija"}, {"options": ["Luksemburg", "Slova\u0161ka"], "key": "Luksemburg::Slova\u0161ka", "selected": "Slova\u0161ka"}, {"options": ["Nem\u010dija", "\u010crna gora"], "key": "Nem\u010dija::\u010crna gora", "selected": "Nem\u010dija"}, {"options": ["Belgija", "Danska"], "key": "Belgija::Danska", "selected": "Belgija"}, {"options": ["Estonija", "Poljska"], "key": "Estonija::Poljska", "selected": "Estonija"}, {"options": ["Luksemburg", "\u010ce\u0161ka"], "key": "Luksemburg::\u010ce\u0161ka", "selected": "\u010ce\u0161ka"}, {"options": ["Belgija", "Tur\u010dija"], "key": "Belgija::Tur\u010dija", "selected": "Belgija"}, {"options": ["Francija", "Finska"], "key": "Francija::Finska", "selected": "Francija"}, {"options": ["Slova\u0161ka", "Slovenija"], "key": "Slova\u0161ka::Slovenija", "selected": "Slovenija"}, {"options": ["Irska", "Poljska"], "key": "Irska::Poljska", "selected": "Irska"}, {"options": ["Nizozemska", "\u010ce\u0161ka"], "key": "Nizozemska::\u010ce\u0161ka", "selected": "\u010ce\u0161ka"}, {"options": ["Latvija", "Srbija"], "key": "Latvija::Srbija", "selected": "Srbija"}, {"options": ["Severna Makedonija", "\u0160vica"], "key": "Severna Makedonija::\u0160vica", "selected": "\u0160vica"}, {"options": ["\u010ce\u0161ka", "Latvija"], "key": "\u010ce\u0161ka::Latvija", "selected": "\u010ce\u0161ka"}, {"options": ["Poljska", "Ciper"], "key": "Poljska::Ciper", "selected": "Poljska"}, {"options": ["Mad\u017earska", "Danska"], "key": "Mad\u017earska::Danska", "selected": "Mad\u017earska"}, {"options": ["Ciper", "Italija"], "key": "Ciper::Italija", "selected": "Italija"}, {"options": ["\u0160vedska", "Srbija"], "key": "\u0160vedska::Srbija", "selected": "\u0160vedska"}, {"options": ["Avstrija", "Srbija"], "key": "Avstrija::Srbija", "selected": "Avstrija"}, {"options": ["Litva", "Islandija"], "key": "Litva::Islandija", "selected": "Litva"}, {"options": ["Bolgarija", "Finska"], "key": "Bolgarija::Finska", "selected": "Finska"}, {"options": ["Mad\u017earska", "Francija"], "key": "Mad\u017earska::Francija", "selected": "Francija"}, {"options": ["Slova\u0161ka", "Italija"], "key": "Slova\u0161ka::Italija", "selected": "Slova\u0161ka"}, {"options": ["Mad\u017earska", "Irska"], "key": "Mad\u017earska::Irska", "selected": "Mad\u017earska"}, {"options": ["\u010crna gora", "Srbija"], "key": "\u010crna gora::Srbija", "selected": "Srbija"}, {"options": ["Portugalska", "\u0160vedska"], "key": "Portugalska::\u0160vedska", "selected": "\u0160vedska"}, {"options": ["Italija", "Nem\u010dija"], "key": "Italija::Nem\u010dija", "selected": "Nem\u010dija"}, {"options": ["Nem\u010dija", "Severna Makedonija"], "key": "Nem\u010dija::Severna Makedonija", "selected": "Nem\u010dija"}, {"options": ["\u010crna gora", "Tur\u010dija"], "key": "\u010crna gora::Tur\u010dija", "selected": "Tur\u010dija"}], "demographicsData": {"age": "0-25", "region": "goriska", "grades": "spomin", "responsibility": "5", "employment": "5", "competition": "4", "gini": "5", "privatization": "5"}}