{"timestamp": "2023-01-10T13:06:09.029Z", "countryPairs": [{"options": ["Srbija", "\u0160panija"], "key": "Srbija::\u0160panija", "selected": "\u0160panija"}, {"options": ["Bolgarija", "Mad\u017earska"], "key": "Bolgarija::Mad\u017earska", "selected": "Mad\u017earska"}, {"options": ["Tur\u010dija", "Latvija"], "key": "Tur\u010dija::Latvija", "selected": "Latvija"}, {"options": ["Italija", "Norve\u0161ka"], "key": "Italija::Norve\u0161ka", "selected": "Italija"}, {"options": ["Latvija", "\u0160vedska"], "key": "Latvija::\u0160vedska", "selected": "\u0160vedska"}, {"options": ["\u0160vedska", "Srbija"], "key": "\u0160vedska::Srbija", "selected": "\u0160vedska"}, {"options": ["\u010crna gora", "Francija"], "key": "\u010crna gora::Francija", "selected": "Francija"}, {"options": ["Portugalska", "Romunija"], "key": "Portugalska::Romunija", "selected": "Portugalska"}, {"options": ["Tur\u010dija", "Francija"], "key": "Tur\u010dija::Francija", "selected": "Francija"}, {"options": ["Avstrija", "Islandija"], "key": "Avstrija::Islandija", "selected": "Avstrija"}, {"options": ["Poljska", "Belgija"], "key": "Poljska::Belgija", "selected": "Belgija"}, {"options": ["Hrva\u0161ka", "Luksemburg"], "key": "Hrva\u0161ka::Luksemburg", "selected": "Luksemburg"}, {"options": ["\u010ce\u0161ka", "\u0160panija"], "key": "\u010ce\u0161ka::\u0160panija", "selected": "\u0160panija"}, {"options": ["Norve\u0161ka", "Ciper"], "key": "Norve\u0161ka::Ciper", "selected": "Norve\u0161ka"}, {"options": ["Slovenija", "Estonija"], "key": "Slovenija::Estonija", "selected": "Slovenija"}, {"options": ["Latvija", "\u010ce\u0161ka"], "key": "Latvija::\u010ce\u0161ka", "selected": "\u010ce\u0161ka"}, {"options": ["Hrva\u0161ka", "\u0160vedska"], "key": "Hrva\u0161ka::\u0160vedska", "selected": "\u0160vedska"}, {"options": ["Severna Makedonija", "Luksemburg"], "key": "Severna Makedonija::Luksemburg", "selected": "Luksemburg"}, {"options": ["Ciper", "Slova\u0161ka"], "key": "Ciper::Slova\u0161ka", "selected": "Slova\u0161ka"}, {"options": ["Italija", "\u0160vica"], "key": "Italija::\u0160vica", "selected": "\u0160vica"}, {"options": ["Belgija", "Avstrija"], "key": "Belgija::Avstrija", "selected": "Avstrija"}, {"options": ["\u010ce\u0161ka", "Islandija"], "key": "\u010ce\u0161ka::Islandija", "selected": "\u010ce\u0161ka"}, {"options": ["Estonija", "Norve\u0161ka"], "key": "Estonija::Norve\u0161ka", "selected": "Norve\u0161ka"}, {"options": ["Slovenija", "Latvija"], "key": "Slovenija::Latvija", "selected": "Slovenija"}, {"options": ["Tur\u010dija", "Finska"], "key": "Tur\u010dija::Finska", "selected": "Tur\u010dija"}, {"options": ["Hrva\u0161ka", "Francija"], "key": "Hrva\u0161ka::Francija", "selected": "Francija"}, {"options": ["Finska", "Bolgarija"], "key": "Finska::Bolgarija", "selected": "Finska"}, {"options": ["Belgija", "Francija"], "key": "Belgija::Francija", "selected": "Belgija"}, {"options": ["Litva", "Severna Makedonija"], "key": "Litva::Severna Makedonija", "selected": "Litva"}, {"options": ["Irska", "Mad\u017earska"], "key": "Irska::Mad\u017earska", "selected": "Irska"}, {"options": ["Norve\u0161ka", "Litva"], "key": "Norve\u0161ka::Litva", "selected": "Norve\u0161ka"}, {"options": ["Islandija", "Bolgarija"], "key": "Islandija::Bolgarija", "selected": "Islandija"}, {"options": ["Latvija", "Mad\u017earska"], "key": "Latvija::Mad\u017earska", "selected": "Latvija"}, {"options": ["\u0160panija", "Estonija"], "key": "\u0160panija::Estonija", "selected": "\u0160panija"}, {"options": ["Portugalska", "Francija"], "key": "Portugalska::Francija", "selected": "Francija"}, {"options": ["Italija", "\u010ce\u0161ka"], "key": "Italija::\u010ce\u0161ka", "selected": "Italija"}, {"options": ["Danska", "Ciper"], "key": "Danska::Ciper", "selected": "Danska"}, {"options": ["Italija", "\u0160vedska"], "key": "Italija::\u0160vedska", "selected": "\u0160vedska"}, {"options": ["Portugalska", "Slovenija"], "key": "Portugalska::Slovenija", "selected": "Portugalska"}, {"options": ["Portugalska", "Luksemburg"], "key": "Portugalska::Luksemburg", "selected": "Luksemburg"}, {"options": ["Luksemburg", "Nem\u010dija"], "key": "Luksemburg::Nem\u010dija", "selected": "Luksemburg"}, {"options": ["Mad\u017earska", "Tur\u010dija"], "key": "Mad\u017earska::Tur\u010dija", "selected": "Tur\u010dija"}, {"options": ["Slovenija", "Nizozemska"], "key": "Slovenija::Nizozemska", "selected": "Nizozemska"}, {"options": ["Nem\u010dija", "Islandija"], "key": "Nem\u010dija::Islandija", "selected": "Nem\u010dija"}, {"options": ["Romunija", "Finska"], "key": "Romunija::Finska", "selected": "Finska"}, {"options": ["Bolgarija", "Portugalska"], "key": "Bolgarija::Portugalska", "selected": "Bolgarija"}, {"options": ["Srbija", "\u010crna gora"], "key": "Srbija::\u010crna gora", "selected": "Srbija"}, {"options": ["Italija", "Estonija"], "key": "Italija::Estonija", "selected": "Italija"}, {"options": ["Finska", "Poljska"], "key": "Finska::Poljska", "selected": "Finska"}, {"options": ["Tur\u010dija", "\u010crna gora"], "key": "Tur\u010dija::\u010crna gora", "selected": "\u010crna gora"}], "demographicsData": {"age": "0-25", "region": "osrednjeslovenska", "grades": "e", "responsibility": "10", "employment": "6", "competition": "6", "gini": "10", "privatization": "1"}}